<?xml version="1.0" encoding="utf-8" ?>
<dwsync>
<file name="._ciframe.html" server="104.238.82.220/web2py/" local="130668060020000000" remote="130899653490000000" Dst="2" />
<file name="._tmpFrameset.html" server="104.238.82.220/web2py/" local="130668060020000000" remote="130899653500000000" Dst="2" />
<file name="._wsc.css" server="104.238.82.220/web2py/" local="130668060020000000" remote="130899653500000000" Dst="2" />
<file name="._wsc.js" server="104.238.82.220/web2py/" local="130668060020000000" remote="130899653500000000" Dst="2" />
<file name="._wsc_ie.js" server="104.238.82.220/web2py/" local="130668060020000000" remote="130899653500000000" Dst="2" />
<file name="ciframe.html" server="104.238.82.220/web2py/" local="130885550837507118" remote="130899653510000000" Dst="2" />
<file name="tmpFrameset.html" server="104.238.82.220/web2py/" local="130885550837617099" remote="130899653510000000" Dst="2" />
<file name="wsc.css" server="104.238.82.220/web2py/" local="130885550837697100" remote="130899653510000000" Dst="2" />
<file name="wsc.js" server="104.238.82.220/web2py/" local="130885550837777145" remote="130899653510000000" Dst="2" />
<file name="wsc_ie.js" server="104.238.82.220/web2py/" local="130885550837827121" remote="130899653520000000" Dst="2" />
</dwsync>